{
    "title": "Mexico profile - Timeline",
    "link": "https://www.bbc.co.uk/news/world-latin-america-18979949",
    "content": [
        {
            "type": "paragraph",
            "content": [
                {
                    "text": "A chronology of key events:",
                    "style": "bold"
                }
            ]
        },
        {
            "type": "paragraph",
            "content": [
                "<bold>1910 </bold>- Beginning of Epic Revolution, triggered by unrest amongst peasants and urban workers, who are led by Emiliano Zapata."
            ]
        },
        {
            "type": "paragraph",
            "content": [
                "<bold>1911 </bold>- Mexico's dictator, Porfirio Diaz, is overthrown. The new president is Francisco Madero, a liberal. Madero introduces land reform and labour legislation. Political unrest continues with Zapata leading a peasant revolt in the south."
            ]
        },
        {
            "type": "paragraph",
            "content": [
                "<bold>1913 </bold>- Madero is assassinated. Victoriano Huerta seizes power."
            ]
        },
        {
            "type": "paragraph",
            "content": [
                "<bold>1914 </bold>- Huerta resigns. He is viewed with suspicion by the United States for his alleged pro-German sympathies. Huerta is succeeded by Venustiano Carranza."
            ]
        },
        {
            "type": "paragraph",
            "content": [
                "<bold>1916 </bold>- US forces cross the border in pursuit of the guerrilla leader Francisco \"Pancho\" Villa."
            ]
        },
        {
            "type": "paragraph",
            "content": [
                "<bold>1917 </bold>- US forces withdraw, having failed to kill Villa. A new constitution is adopted, which is designed to ensure permanent democracy in Mexico."
            ]
        },
        {
            "type": "paragraph",
            "content": [
                "<bold>1920 </bold>- Carranza is murdered. Civil war follows."
            ]
        },
        {
            "type": "paragraph",
            "content": [
                "<bold>1929 </bold>- The National Revolutionary Party is formed. In 1946 it is re-named the Institutional Revolutionary Party, or PRI."
            ]
        },
        {
            "type": "paragraph",
            "content": [
                "<bold>1934 </bold>- President Lazaro Cardenas begins programme of oil nationalisation, land reform and industrial expansion."
            ]
        },
        {
            "type": "paragraph",
            "content": [
                "<bold>1940 </bold>- Leon Trotsky murdered in Mexico."
            ]
        },
        {
            "type": "paragraph",
            "content": [
                "<bold>1942 </bold>- Mexico declares war on Japan and Germany."
            ]
        },
        {
            "type": "paragraph",
            "content": [
                "<bold>1960s </bold>- Unrest amongst peasants and labourers over unequal wealth distribution is suppressed."
            ]
        },
        {
            "type": "paragraph",
            "content": [
                "<bold>1968 </bold>- Student demonstration in Tlatelolco, Mexico City, during the Olympic Games is fired upon by Mexican security forces. Hundreds of protestors are killed or wounded. The extent of the violence shocks the country."
            ]
        },
        {
            "type": "paragraph",
            "content": [
                "<bold>1976 </bold>- Huge offshore oil reserves discovered; the Cantarell field becomes the mainstay of Mexico's oil production."
            ]
        },
        {
            "type": "paragraph",
            "content": [
                "<bold>1985 </bold>- Earthquake in Mexico City kills thousands and makes many more homeless."
            ]
        },
        {
            "type": "paragraph",
            "content": [
                "<bold>1993 </bold>- Mexican parliament ratifies the North American Free Trade Agreement (Nafta) with the US and Canada."
            ]
        },
        {
            "type": "paragraph",
            "content": [
                "<bold>1994 </bold>- A guerrilla rebellion in Chiapas by the Zapatista National Liberation Army is brutally suppressed by government troops. The rebels oppose Nafta and want greater recognition for Indian rights. The government recognises the Zapatista National Liberation Front (EZLN)."
            ]
        },
        {
            "type": "paragraph",
            "content": [
                "<bold>1994 </bold>August - Presidential elections won by PRI candidate Ernesto Zedillo Ponce de Leon, after the previous candidate, Luis Donaldo Colosio, was murdered. The stock market plunges in December, the peso loses a third of its value."
            ]
        },
        {
            "type": "paragraph",
            "content": [
                "<bold>1995 </bold>- Former President Carlos Salinas goes into exile after his brother Raul Salinas is connected with Colosio's murder."
            ]
        },
        {
            "type": "paragraph",
            "content": [
                "<bold>1995 </bold>November - The government and the EZLN reach an agreement on greater autonomy for the indigenous Mayans of Chiapas."
            ]
        },
        {
            "type": "paragraph",
            "content": [
                "<bold>1996 </bold>- The insurgency in the south escalates as the leftist Popular Revolutionary Army (EPR) attacks government troops."
            ]
        },
        {
            "type": "paragraph",
            "content": [
                "<bold>1997 </bold>- The PRI suffers heavy losses in elections and loses its overall majority in the lower house of parliament for the first time since 1929."
            ]
        },
        {
            "type": "paragraph",
            "content": [
                "<bold>1997 </bold>December - 45 Indians killed by paramilitary gunmen in a Chiapas village. The incident causes an international outcry, President Zedillo starts an investigation."
            ]
        },
        {
            "type": "paragraph",
            "content": [
                "<bold>1998 </bold>January - Governor of Chiapas resigns. Peace talks with the rebels are reactivated, but break down at the end of the year."
            ]
        },
        {
            "type": "paragraph",
            "content": [
                "<bold>2000 </bold>July - Vicente Fox of the opposition Alliance for Change wins presidential elections, the first opposition candidate ever to do so. Parliamentary elections see the Alliance for Change emerge as the strongest party, beating the PRI by just over 1%."
            ]
        },
        {
            "type": "paragraph",
            "content": [
                "<bold>2001 </bold>March - Zapatista guerrillas, led by Subcomandante Marcos, stage their 'Zapatour', a march from Chiapas to Mexico City to highlight their demands."
            ]
        },
        {
            "type": "paragraph",
            "content": [
                "<bold>2001 </bold>April - Parliament passes a bill increasing the rights of indigenous people. A few days later, Subcomandante Marcos rejects the bill, saying it leaves the Indian population worse off than before. Marcos says the uprising in Chiapas will continue."
            ]
        },
        {
            "type": "paragraph",
            "content": [
                "<bold>2001 </bold>November - President Fox appoints a prosecutor to investigate the disappearance of left-wing activists during the 1970s and 1980s."
            ]
        },
        {
            "type": "paragraph",
            "content": [
                "<bold>2002 </bold>March - Roberto Madrazo wins the contest to lead the PRI, which governed for 71 years until 2000."
            ]
        },
        {
            "type": "paragraph",
            "content": [
                "<bold>2002 </bold>June - Millions of secret security files are released, shedding light on the torture and killing by security forces of hundreds of political activists in the 1960s and 1970s. President Fox says his government is not afraid to pursue prosecutions."
            ]
        },
        {
            "type": "paragraph",
            "content": [
                "<bold>2002 </bold>July - Former President Luis Echeverria is questioned about massacres of student protesters in 1968, when he was interior minister, and in 1971 when he was president."
            ]
        },
        {
            "type": "paragraph",
            "content": [
                "<bold>2002 </bold>September - Three army officers are charged with first-degree murder over the killings of 134 leftists in the 1970s."
            ]
        },
        {
            "type": "paragraph",
            "content": [
                "<bold>2004 </bold>July - Investigator deems 1971 shooting of student protesters by government forces to have been genocide; judge refuses to order arrest of former President Luis Echeverria on charges that he ordered attack."
            ]
        },
        {
            "type": "paragraph",
            "content": [
                "<bold>2005 </bold>January - Six prison officers are murdered and top-security jails are put on high alert amid escalating tension between the authorities and drug gangs."
            ]
        },
        {
            "type": "paragraph",
            "content": [
                "<bold>2005 </bold>April - Political furore as Mexico City mayor and presidential favourite Andres Manuel Lopez Obrador is stripped of his immunity from prosecution by Congress in a land dispute. The government eventually abandons the prosecution."
            ]
        },
        {
            "type": "paragraph",
            "content": [
                "<bold>2006 </bold>February - A federal post of special prosecutor is created to tackle violent crime against women. Mexico had been criticised by the UN and rights groups over the unsolved murders of more than 300 women over 12 years in the border city of Ciudad Juarez."
            ]
        },
        {
            "type": "paragraph",
            "content": [
                "65 miners are killed in an explosion at a coal mine in Coahuila state. President Fox orders an investigation."
            ]
        },
        {
            "type": "paragraph",
            "content": [
                "<bold>2006 </bold>July - Conservative candidate Felipe Calderon is declared the winner of presidential elections with a razor-thin majority over his leftist rival, Andres Manuel Lopez Obrador, who challenges the result with mass street protests. The Federal Electoral Tribunal confirms Mr Calderon's win in September."
            ]
        },
        {
            "type": "paragraph",
            "content": [
                "<bold>2006 </bold>October - US President George W Bush signs legislation to build 1,125km (700 miles) of fencing along the US-Mexico border. Mexico condemns plans for the barrier, which is intended to curb illegal immigration."
            ]
        },
        {
            "type": "paragraph",
            "content": [
                "<bold>2006 </bold>December - A new federal police force is created to tackle drugs cartels; thousands of troops are deployed in the western state of Michoacan as part of a major anti-drug trafficking drive."
            ]
        },
        {
            "type": "paragraph",
            "content": [
                "<bold>2007 </bold>February - New law obliging authorities to take tougher action against domestic violence comes into effect."
            ]
        },
        {
            "type": "paragraph",
            "content": [
                "<bold>2007 </bold>July - A financial website says that Mexican telecoms tycoon Carlos Slim has overtaken Microsoft founder Bill Gates to become the world's richest person."
            ]
        },
        {
            "type": "paragraph",
            "content": [
                "Genocide trial against former president Luis Echeverria is suspended."
            ]
        },
        {
            "type": "paragraph",
            "content": [
                "<bold>2007 </bold>October - Heavy rains flood nearly the entire southern state of Tabasco. Some 500,000 are made homeless in one of the country's worst natural disasters."
            ]
        },
        {
            "type": "paragraph",
            "content": [
                "<bold>2008 </bold>Drug-related killings soar. Murders linked to organised crime leap to almost 1,400 in first five months of year."
            ]
        },
        {
            "type": "paragraph",
            "content": [
                "<bold>2008 </bold>May - Attorney-general Eduardo Medina Mora says more than 4,000 people have been killed in 18 months since President Calderon took office and declared war on drugs cartels. About 450 of the dead are police, soldiers or prosecutors, and many of the killings have been concentrated along the US border."
            ]
        },
        {
            "type": "paragraph",
            "content": [
                "<bold>2008 </bold>August - Hundreds of thousands join marches throughout Mexico to protest against continuing wave of drugs-related violence."
            ]
        },
        {
            "type": "paragraph",
            "content": [
                "<bold>2008 </bold>October - Faced with drop in Mexican oil production, government passes series of energy reforms. Package includes controversial plans to allow private investment in state oil giant Pemex."
            ]
        },
        {
            "type": "paragraph",
            "content": [
                "<bold>2009 </bold>January - Government unveils package of emergency measures worth nearly $150m (£100m) to protect economy from effects of US economic downturn."
            ]
        },
        {
            "type": "paragraph",
            "content": [
                "<bold>2009 </bold>February - Reports say about 1,000 people died in a further upsurge in drug-related violence in the first six weeks of 2009."
            ]
        },
        {
            "type": "paragraph",
            "content": [
                "<bold>2009 </bold>March - Army troops enter Ciudad Juarez, on the border with the US, as open warfare erupts between rival drug gangs."
            ]
        },
        {
            "type": "paragraph",
            "content": [
                "<bold>2009 </bold>April - Authorities close schools and public buildings after dozens are confirmed to have been killed by the virulent new swine flu virus."
            ]
        },
        {
            "type": "paragraph",
            "content": [
                "<bold>2009 </bold>July - Opposition Institutional Revolutionary Party (PRI) makes large gains in mid-term congressional elections, winning 48% of seats in the Chamber of Deputies."
            ]
        },
        {
            "type": "paragraph",
            "content": [
                "<bold>2009 </bold>October - Murder rate in Ciudad Juarez on Mexico-US border reaches all-time high amid battles between rival drug cartels."
            ]
        },
        {
            "type": "paragraph",
            "content": [
                "<bold>2009 </bold>December - One of Mexico's most-wanted drug lords, Arturo Beltran Leyva, is killed in a shoot-out with state security forces."
            ]
        },
        {
            "type": "paragraph",
            "content": [
                "The authorities put the number of drug-related killings for 2009 at around 6,500, the worst year of bloodshed since President Felipe Calderon declared war on the drug cartels in late 2006."
            ]
        },
        {
            "type": "paragraph",
            "content": [
                "<bold>2010 </bold>March - President Calderon calls on United States to share responsibility in battle against drug trafficking, after murder of three people connected to US consulate in border city of Ciudad Juarez."
            ]
        },
        {
            "type": "paragraph",
            "content": [
                "<bold>2010 </bold>August - US President Barack Obama signs into law a $600m bill to put more agents and equipment along the Mexican border to stem the flow of illegal immigrants."
            ]
        },
        {
            "type": "paragraph",
            "content": [
                "<bold>2010 </bold>December - Wikileaks releases US diplomatic cables revealing that the US ambassador questioned the Mexican security forces' ability to tackle organised crime."
            ]
        },
        {
            "type": "paragraph",
            "content": [
                "<bold>2011 </bold>April - Thousands participate in protests across Mexico against drug-related violence. The marches are called by Mexican poet Javier Sicilia, whose son was murdered in March 2011; protests continue throughout the summer."
            ]
        },
        {
            "type": "paragraph",
            "content": [
                "<bold>2011 </bold>June-July - Two crime journalists, Miguel Angel Lopez Velasco and Yolanda Ordaz de la Cruz, are killed in separate incidents."
            ]
        },
        {
            "type": "paragraph",
            "content": [
                "<bold>2011 </bold>August - An attack on the Casino Royale in Monterrey kills 52 people, after gunmen douse the building with fuel and set it alight. President Calderon describes the attack as \"an abhorrent act of terror.\""
            ]
        },
        {
            "type": "paragraph",
            "content": [
                "<bold>2012 </bold>May - The army arrests a drug cartel leader over the killing of 49 people whose mutilated bodies are dumped on a major road in Nuevo Leon state. The massacre is one of the worst atrocities committed in the ongoing drug war."
            ]
        },
        {
            "type": "paragraph",
            "content": [
                "<bold>2012 </bold>July - Enrique Pena Nieto wins presidential election."
            ]
        }
    ]
}